{"time":1283126460354,"numEdits":6023,"uniqueips":["192.168.1.115","127.0.0.1"],"categorycounter":{"/education/educational_institution":9,"/education/school":8,"/business/employer":26,"/location/location":45,"/organization/organization":23,"/biology/organism_classification":8,"/food/ingredient":3,"/medicine/drug":2,"/medicine/medical_treatment":2,"/food/food":3,"/people/person":96,"/book/author":17,"/business/board_member":8,"/government/politician":1,"/government/political_appointer":1,"/royalty/chivalric_order_member":1,"/award/award_winner":10,"/military/military_person":5,"/film/film_character":5,"/fictional_universe/fictional_character":6,"/tv/tv_actor":20,"/organization/organization_founder":5,"/sports/sport":1,"/martial_arts/martial_art":1,"/olympics/olympic_sport":1,"/book/book_subject":20,"/location/citytown":14,"/location/dated_location":24,"/location/statistical_region":24,"/location/hud_county_place":5,"/location/hud_foreclosure_area":5,"/film/producer":4,"/influence/influence_node":22,"/music/artist":27,"/music/musical_group":11,"/internet/social_network_user":16,"/book/written_work":6,"/film/actor":23,"/music/group_member":9,"/tv/tv_personality":3,"/book/book":4,"/fictional_universe/work_of_fiction":2,"/soccer/football_team":12,"/sports/sports_team":12,"/tv/tv_program":11,"/automotive/model":3,"/education/school_district":4,"/location/administrative_division":8,"/location/mx_state":2,"/government/governmental_jurisdiction":12,"/film/writer":2,"/people/deceased_person":32,"/award/award_nominee":14,"/broadcast/artist":8,"/award/award_category":1,"/film/director":2,"/film/person_or_entity_appearing_in_film":4,"/book/journal":3,"/book/periodical":3,"/film/film_subject":3,"/media_common/quotation_subject":2,"/visual_art/art_subject":5,"/location/country":9,"/organization/organization_member":11,"/olympics/olympic_participating_country":9,"/sports/sports_team_location":11,"/military/military_combatant":8,"/film/film_location":8,"/sports/boxer":2,"/olympics/olympic_athlete":6,"/ice_hockey/hockey_player":1,"/sports/pro_athlete":3,"/people/measured_person":3,"/tv/non_character_role":1,"/fictional_universe/character_occupation":1,"/fictional_universe/character_rank":1,"/film/film_cut_type":1,"/language/human_language":3,"/theater/theater_actor":1,"/celebrities/celebrity":2,"/food/diet_follower":1,"/location/symbol_of_administrative_division":1,"/soccer/football_player":10,"/fictional_universe/fictional_universe":1,"/aviation/aircraft_model":3,"/education/academic":3,"/business/brand":1,"/tv/tv_producer":2,"/tv/tv_director":2,"/computer/file_format":1,"/geography/lake":2,"/geography/body_of_water":2,"/geography/geographical_feature":2,"/award/award_winning_work":7,"/visual_art/visual_art_genre":2,"/people/profession":3,"/cvg/game_voice_actor":1,"/medicine/disease":1,"/medicine/symptom":1,"/music/album":8,"/tv/tv_character":1,"/royalty/system_of_nobility":1,"/business/business_location":1,"/government/government":3,"/music/producer":1,"/music/lyricist":2,"/music/composer":2,"/people/family_name":1,"/film/film":6,"/media_common/adaptation":3,"/award/award_nominated_work":5,"/internet/website":5,"/award/ranked_item":5,"/baseball/baseball_player":2,"/business/company_advisor":1,"/people/ethnicity":2,"/fictional_universe/ethnicity_in_fiction":2,"/music/composition":1,"/travel/tourist_attraction":1,"/architecture/building":5,"/architecture/structure":6,"/projects/project_focus":5,"/protected_sites/listed_site":1,"/location/uk_civil_parish":2,"/martial_arts/martial_artist":1,"/book/book_character":3,"/fictional_universe/fictional_organization_founder":1,"/architecture/building_function":1,"/food/dish":2,"/business/business_operation":5,"/medicine/hospital":2,"/organization/membership_organization":1,"/religion/religion":1,"/cvg/computer_videogame":6,"/aviation/aircraft_owner":3,"/military/armed_force":1,"/time/event":3,"/military/military_conflict":2,"/sports/sports_award_winner":1,"/fictional_universe/person_in_fiction":3,"/visual_art/visual_artist":1,"/book/illustrator":1,"/sports/golfer":4,"/food/beer_country_region":2,"/location/region":2,"/biology/breed_origin":2,"/royalty/kingdom":2,"/sports/sport_country":2,"/organization/organization_scope":2,"/media_common/netflix_genre":2,"/event/speech_topic":1,"/metropolitan_transit/transit_stop":1,"/sports/sports_league":1,"/medicine/physician":1,"/medicine/notable_person_with_medical_condition":3,"/people/family_member":1,"/film/film_genre":1,"/media_common/media_genre":1,"/tv/tv_network":1,"/architecture/house":1,"/measurement_unit/temperature_unit":1,"/type/unit":1,"/freebase/unit_profile":1,"/games/game":1,"/travel/travel_destination":1,"/location/fr_department":1,"/government/political_party":2,"/tv/tv_program_guest":1,"/fashion/fashion_designer":1,"/location/neighborhood":1},"categorynamebyid":{"/tv/tv_program":"TV Program","/award/award_nominated_work":"Award-Nominated Work","/media_common/adaptation":"Adaptation","/internet/website":"Website","/book/author":"Author","/film/film":"Film","/award/ranked_item":"Ranked item","/music/album":"Musical Album","/people/person":"Person","/film/actor":"Film actor","/tv/tv_actor":"TV Actor","/influence/influence_node":"Influence Node","/award/award_nominee":"Award Nominee","/baseball/baseball_player":"Baseball Player","/sports/pro_athlete":"Pro Athlete","/people/measured_person":"Measured person","/people/deceased_person":"Deceased Person","/sports/boxer":"Boxer","/soccer/football_player":"Football player","/award/award_winning_work":"Award-Winning Work","/business/board_member":"Organization leader","/business/company_advisor":"Organization advisor","/organization/organization_founder":"Organization founder","/education/academic":"Academic","/award/award_winner":"Award Winner","/people/ethnicity":"Ethnicity","/fictional_universe/ethnicity_in_fiction":"Ethnicity in fiction","/business/employer":"Employer","/internet/social_network_user":"Social network user","/music/artist":"Musical Artist","/music/group_member":"Musician","/film/person_or_entity_appearing_in_film":"Person or entity appearing in film","/education/educational_institution":"Educational Institution","/education/school":"School","/education/school_district":"School district","/location/location":"Location","/organization/organization":"Organization","/music/musical_group":"Musical Group","/music/composition":"Composition","/travel/tourist_attraction":"Tourist attraction","/architecture/building":"Building","/architecture/structure":"Structure","/projects/project_focus":"Project focus","/protected_sites/listed_site":"Listed Site","/location/citytown":"City/Town","/location/dated_location":"Dated location","/location/statistical_region":"Statistical region","/location/uk_civil_parish":"English civil parish","/location/administrative_division":"Administrative Division","/soccer/football_team":"Football team","/sports/sports_team":"Sports Team","/martial_arts/martial_artist":"Martial Artist","/fictional_universe/fictional_character":"Fictional Character","/book/book_character":"Book Character","/film/film_character":"Film character","/fictional_universe/fictional_organization_founder":"Fictional Organization Founder","/architecture/building_function":"Building function","/food/dish":"Dish","/business/business_operation":"Business Operation","/olympics/olympic_athlete":"Olympic athlete","/medicine/hospital":"Hospital","/organization/membership_organization":"Membership organization","/religion/religion":"Religion","/cvg/computer_videogame":"Video Game","/aviation/aircraft_owner":"Aircraft Owner","/book/book_subject":"Literature Subject","/military/armed_force":"Armed Force","/time/event":"Event","/military/military_conflict":"Military Conflict","/sports/sports_award_winner":"Sports League Award Winner","/visual_art/art_subject":"Art Subject","/organization/organization_member":"Organization member","/fictional_universe/person_in_fiction":"Person Or Being In Fiction","/military/military_person":"Military Person","/visual_art/visual_artist":"Visual Artist","/film/film_subject":"Film subject","/book/illustrator":"Illustrator","/sports/golfer":"Golfer","/biology/organism_classification":"Organism Classification","/location/country":"Country","/military/military_combatant":"Military Combatant","/food/beer_country_region":"Beer country / region","/olympics/olympic_participating_country":"Olympic participating country","/government/governmental_jurisdiction":"Governmental Jurisdiction","/location/region":"Region","/government/government":"Government","/biology/breed_origin":"Breed origin","/sports/sports_team_location":"Sports Team Location","/royalty/kingdom":"Kingdom","/sports/sport_country":"Sport Country","/organization/organization_scope":"Organization scope","/language/human_language":"Human Language","/media_common/netflix_genre":"Netflix Genre","/event/speech_topic":"Speech topic","/film/film_location":"Filming location","/metropolitan_transit/transit_stop":"Transit Stop","/people/profession":"Profession","/sports/sports_league":"Sports Association","/geography/lake":"Lake","/geography/body_of_water":"Body Of Water","/geography/geographical_feature":"Geographical Feature","/film/producer":"Film producer","/medicine/physician":"Physician","/medicine/notable_person_with_medical_condition":"Public figure with medical condition","/people/family_member":"Family member","/film/film_genre":"Film genre","/media_common/media_genre":"Media genre","/food/ingredient":"Ingredient","/food/food":"Food","/tv/tv_network":"TV Network","/location/hud_county_place":"HUD County Place","/location/hud_foreclosure_area":"HUD Foreclosure Area","/media_common/quotation_subject":"Quotation Subject","/architecture/house":"House","/measurement_unit/temperature_unit":"Unit Of Temperature","/type/unit":"Unit","/freebase/unit_profile":"Unit Profile","/games/game":"Game","/automotive/model":"Automobile Model","/travel/travel_destination":"Travel destination","/location/fr_department":"French Department","/government/political_party":"Political party","/broadcast/artist":"Broadcast Artist","/music/lyricist":"Lyricist","/music/composer":"Composer","/tv/tv_program_guest":"TV program guest","/fashion/fashion_designer":"Fashion designer","/location/neighborhood":"Neighborhood"}}